foliant/preprocessors/pgsqldoc/__init__.py
foliant/preprocessors/pgsqldoc/pgsqldoc.py
foliant/preprocessors/pgsqldoc/queries.py
foliant/preprocessors/pgsqldoc/utils.py
foliant/preprocessors/pgsqldoc/templates/pgsqldoc.j2
foliant/preprocessors/pgsqldoc/templates/scheme.j2
foliantcontrib.pgsqldoc-1.1.7.dist-info/LICENSE
foliantcontrib.pgsqldoc-1.1.7.dist-info/METADATA
foliantcontrib.pgsqldoc-1.1.7.dist-info/WHEEL
foliantcontrib.pgsqldoc-1.1.7.dist-info/top_level.txt
foliantcontrib.pgsqldoc-1.1.7.dist-info/RECORD
