Metadata-Version: 2.1
Name: foliantcontrib.pgsqldoc
Version: 1.1.7
Summary: Documentation generator for PostgreSQL DB
Home-page: UNKNOWN
Author: Daniil Minukhin
Author-email: ddddsa@gmail.com
License: MIT
Platform: any
Classifier: Development Status :: 5 - Production/Stable
Classifier: Environment :: Console
Classifier: Intended Audience :: Developers
Classifier: License :: OSI Approved :: MIT License
Classifier: Operating System :: OS Independent
Classifier: Programming Language :: Python
Classifier: Topic :: Documentation
Classifier: Topic :: Utilities
Requires-Dist: PyYAML
Requires-Dist: foliant (>=1.0.5)
Requires-Dist: foliantcontrib.plantuml
Requires-Dist: foliantcontrib.utils (>=1.0.2)
Requires-Dist: jinja2
Requires-Dist: psycopg2-binary
